api.py
adapters/akshare_adapter.py
adapters/base.py
adapters/ccxt_adapter.py
adapters/yfinance_adapter.py
models/__init__.py
models/enums.py
jokerssd_data_api-0.1.0.dist-info/METADATA
jokerssd_data_api-0.1.0.dist-info/WHEEL
jokerssd_data_api-0.1.0.dist-info/top_level.txt
jokerssd_data_api-0.1.0.dist-info/RECORD
