Metadata-Version: 2.4
Name: jokerssd-data-api
Version: 0.1.0
Summary: Add your description here
Requires-Python: >=3.12
Requires-Dist: akshare>=1.18.4
Requires-Dist: ccxt>=4.5.30
Requires-Dist: polars>=1.36.1
Requires-Dist: pyarrow>=22.0.0
Requires-Dist: yfinance>=1.0
